pyproject.toml
setup.py
alkira/__init__.py
alkira/sdk.py
alkira_sdk.egg-info/PKG-INFO
alkira_sdk.egg-info/SOURCES.txt
alkira_sdk.egg-info/dependency_links.txt
alkira_sdk.egg-info/requires.txt
alkira_sdk.egg-info/top_level.txt