Metadata-Version: 2.1
Name: alkira-sdk
Version: 1.0.1
Summary: A Python SDK for interacting with Alkira
Home-page: UNKNOWN
Author: Hemat Kumar <hemant4.kumar@orange.com>
License: UNKNOWN
Platform: UNKNOWN
